ehelply_updater/__init__.py
ehelply_updater/ehelply_updater.py
ehelply_updater/updater.py
ehelply_updater-0.2.0.dist-info/LICENSE
ehelply_updater-0.2.0.dist-info/WHEEL
ehelply_updater-0.2.0.dist-info/METADATA
ehelply_updater-0.2.0.dist-info/RECORD
