Metadata-Version: 2.1
Name: ehelply-updater
Version: 0.2.0
Summary: 
Home-page: https://ehelply.com
Author: Shawn Clake
Author-email: shawn.clake@gmail.com
Requires-Python: >=3.10
Classifier: Programming Language :: Python :: 3
Requires-Dist: click (>=8.1.2,<9.0.0)
Requires-Dist: ehelply-logger (>=0.0.8,<0.0.9)
Requires-Dist: pydantic (>=1.9.0,<2.0.0)
Requires-Dist: python-slugify (>=6.1.1,<7.0.0)
Requires-Dist: requests (>=2.27.1,<3.0.0)
Requires-Dist: wheel (>=0.37.1,<0.38.0)
